scrapengine/__init__.py
scrapengine/_base_client.py
scrapengine/_client.py
scrapengine/_compat.py
scrapengine/_constants.py
scrapengine/_exceptions.py
scrapengine/_files.py
scrapengine/_models.py
scrapengine/_qs.py
scrapengine/_resource.py
scrapengine/_response.py
scrapengine/_streaming.py
scrapengine/_types.py
scrapengine/_version.py
scrapengine/py.typed
scrapengine/_utils/__init__.py
scrapengine/_utils/_compat.py
scrapengine/_utils/_datetime_parse.py
scrapengine/_utils/_logs.py
scrapengine/_utils/_proxy.py
scrapengine/_utils/_reflection.py
scrapengine/_utils/_resources_proxy.py
scrapengine/_utils/_streams.py
scrapengine/_utils/_sync.py
scrapengine/_utils/_transform.py
scrapengine/_utils/_typing.py
scrapengine/_utils/_utils.py
scrapengine/lib/.keep
scrapengine/resources/__init__.py
scrapengine/resources/amazon.py
scrapengine/resources/bing.py
scrapengine/resources/google.py
scrapengine/resources/lazada.py
scrapengine/resources/scrape.py
scrapengine/types/__init__.py
scrapengine/types/amazon_search_params.py
scrapengine/types/amazon_search_response.py
scrapengine/types/bing_search_params.py
scrapengine/types/bing_search_response.py
scrapengine/types/google_search_params.py
scrapengine/types/google_search_response.py
scrapengine/types/lazada_search_params.py
scrapengine/types/lazada_search_response.py
scrapengine/types/scrape_create_params.py
scrapengine/types/scrape_create_response.py
scrapengine/types/scrape_get_status_response.py
scrapengine_sdk_python-0.3.0.dist-info/METADATA
scrapengine_sdk_python-0.3.0.dist-info/WHEEL
scrapengine_sdk_python-0.3.0.dist-info/licenses/LICENSE
scrapengine_sdk_python-0.3.0.dist-info/RECORD
